[
    {
        "categoria": "antipasti",
        "nome": "Muschelsuppe",
        "prezzo": "12.00€",
        "immagine": "assets/piatti/cozze.webp",
        "allergeni": "1/11/13"
    },
    {
        "categoria": "antipasti",
        "nome": "Rohe Meeresfrüchte",
        "prezzo": "28.00€",
        "immagine": "assets/piatti/crudi.webp",
        "allergeni": "2/4/13/14"
    },
    {
        "categoria": "antipasti",
        "nome": "Austern",
        "prezzo": "4.00€ pro Stück",
        "immagine": "assets/piatti/ostriche.webp",
        "allergeni": "13"
    },
    {
        "categoria": "antipasti",
        "nome": "Fischdelikatessen warm und kalt",
        "prezzo": "18.00€ - 6 Kostproben",
        "immagine": "assets/piatti/sfiziosita_pesce.webp",
        "allergeni": "4/14"
    },
    {
        "categoria": "antipasti",
        "nome": "Trio von Tartar (Thunfisch, Schwertfisch, Lachs)",
        "prezzo": "18.00€",
        "immagine": "assets/piatti/tris_tartare.webp",
        "allergeni": "4/14"
    },
    {
        "categoria": "antipasti",
        "nome": "Meeresfrüchtesalat",
        "prezzo": "16.00€",
        "immagine": "assets/piatti/insalata_mare.webp",
        "allergeni": "2/4/13"
    },
    {
        "categoria": "antipasti",
        "nome": "*Luciana-Stil Babyoctopus",
        "prezzo": "12.00€",
        "immagine": "assets/piatti/polipetti_luciana.webp",
        "allergeni": "1/13"
    },
    {
        "categoria": "antipasti",
        "nome": "*Octopus mit Kartoffeln",
        "prezzo": "16.00€",
        "immagine": "assets/piatti/polpo_patate.webp",
        "allergeni": "6/13"
    },
    {
        "categoria": "antipasti",
        "nome": "Platte mit Aufschnitt, Crostini und D.O.P. Käse mit Landfantasien",
        "prezzo": "20.00€",
        "immagine": "assets/piatti/tagliere_salumi.webp",
        "allergeni": "1/3/6/7/9"
    },
    {
        "nome": "Spaghetti mit Venusmuscheln",
        "categoria": "Primi",
        "prezzo": "16.00€",
        "immagine": "assets/piatti/spaghetti_alle_vongole_veraci.webp",
        "allergeni": "1/13"
    },
    {
        "nome": "Risotto mit Scampi-Creme",
        "categoria": "Primi",
        "prezzo": "14.00€",
        "immagine": "assets/piatti/risotto_alla_crema_di_scampi.webp",
        "allergeni": "2/7"
    },
    {
        "nome": "*Fischer-Risotto",
        "categoria": "Primi",
        "prezzo": "15.00€",
        "immagine": "assets/piatti/risotto_alla_pescatora.webp",
        "allergeni": "2/4/13"
    },
    {
        "nome": "Linguine mit Hummer",
        "categoria": "Primi",
        "prezzo": "22.00€",
        "immagine": "assets/piatti/linguine_allastice.webp",
        "allergeni": "1/2"
    },
    {
        "nome": "Tonnarelli mit Meeresfrüchten",
        "categoria": "Primi",
        "prezzo": "16.00€",
        "immagine": "assets/piatti/tonnarelli_allo_scoglio.webp",
        "allergeni": "2/4/13"
    },
    {
        "nome": "Gnocchi mit Schwertfisch und Pistazie",
        "categoria": "Primi",
        "prezzo": "14.00€",
        "immagine": "assets/piatti/gnocchi_pesce_spada_e_pistacchio.webp",
        "allergeni": "1/4"
    },
    {
        "nome": "Carbonara",
        "categoria": "Primi",
        "prezzo": "13.00€",
        "immagine": "assets/piatti/carbonara.webp",
        "allergeni": "3/7"
    },
    {
        "nome": "Cacio e pepe",
        "categoria": "Primi",
        "prezzo": "13.00€",
        "immagine": "assets/piatti/cacio_e_pepe.webp",
        "allergeni": "3/7"
    },
    {
        "categoria": "secondi",
        "nome": "Gegrillter Fisch",
        "prezzo": "24.00€",
        "immagine": "assets/piatti/grigliata_pesce.webp",
        "allergeni": "2/4/13"
    },
    {
        "categoria": "secondi",
        "nome": "*Frittierte Calamari und Garnelen",
        "prezzo": "16.00€",
        "immagine": "assets/piatti/frittura_calamar_gamberi.webp",
        "allergeni": "2/4/13"
    },
    {
        "categoria": "secondi",
        "nome": "Fischmischung",
        "prezzo": "24.00€",
        "immagine": "assets/piatti/miscuglio_pesce.webp",
        "allergeni": "2/3/4/13"
    },
    {
        "categoria": "secondi",
        "nome": "Thunfischsteak",
        "prezzo": "18.00€",
        "immagine": "assets/piatti/tagliata_tonno.webp",
        "allergeni": "4/5/6/14"
    },
    {
        "categoria": "secondi",
        "nome": "Gebackener Steinbutt mit Kartoffeln",
        "prezzo": "6.50 pro 100g",
        "immagine": "assets/piatti/rombo_patate.webp",
        "allergeni": "4"
    },
    {
        "categoria": "secondi",
        "nome": "Gebackener Fang des Tages mit Kartoffeln",
        "prezzo": "6.50 pro 100g",
        "immagine": "assets/piatti/pescato_patate.webp",
        "allergeni": "4"
    },
    {
        "categoria": "secondi",
        "nome": "Gebackener Zucht-Dorade mit Kartoffeln",
        "prezzo": "18.00€",
        "immagine": "assets/piatti/orata_patate.webp",
        "allergeni": "4"
    },
    {
        "categoria": "secondi",
        "nome": "Fischsuppe",
        "prezzo": "55.00€",
        "immagine": "assets/piatti/zuppa_pesce.webp",
        "allergeni": "2/3/4/13"
    },
    {
        "categoria": "secondi",
        "nome": "Krustentiersuppe",
        "prezzo": "60.00€",
        "immagine": "assets/piatti/zuppa_crostacei.webp",
        "allergeni": "2/3/13"
    },
    {
        "categoria": "secondi",
        "nome": "Knuspriges Lachsfilet mit Kräutern",
        "prezzo": "18.00€",
        "immagine": "assets/piatti/salmone_erbe.webp",
        "allergeni": "2/3/13"
    },
    {
        "categoria": "secondi",
        "nome": "Rindersteak",
        "prezzo": "18.00€",
        "immagine": "assets/piatti/bistecca_manzo.webp",
        "allergeni": "1/6"
    },
    {
        "categoria": "contorni",
        "nome": "Gemischter oder grüner Salat",
        "prezzo": "5.00€",
        "immagine": "assets/piatti/insalata_mista.webp"
    },
    {
        "categoria": "contorni",
        "nome": "*Pommes frites oder Ofenkartoffeln",
        "prezzo": "5.00€",
        "immagine": "assets/piatti/patatine_fritte_forno.webp",
        "allergeni": "1"
    },
    {
        "categoria": "contorni",
        "nome": "Gebratener Chicorée oder mit Essig",
        "prezzo": "5.00€",
        "immagine": "assets/piatti/cicoria_ripassata.webp",
        "allergeni": "1"
    },
    {
        "categoria": "da bere",
        "nome": "Mineralwasser",
        "prezzo": "2.50",
        "immagine": "assets/piatti/acqua_minerale.webp"
    },
    {
        "categoria": "da bere",
        "nome": "Bier – 0.25l",
        "prezzo": "4.00€",
        "immagine": "assets/piatti/birra_025l.webp"
    },
    {
        "categoria": "da bere",
        "nome": "Fanta/Cola/Sprite",
        "prezzo": "3.00€",
        "immagine": "assets/piatti/fanta_cola_sprite.webp"
    },
    {
        "categoria": "da bere",
        "nome": "Bier – 0.5l",
        "prezzo": "6.00€",
        "immagine": "assets/piatti/birra_05l.webp"
    },
    {
        "categoria": "da bere",
        "nome": "Pfirsich/Zitrone Eistee",
        "prezzo": "3.00€",
        "immagine": "assets/piatti/the_freddo.webp"
    },
    {
        "categoria": "da bere",
        "nome": "Fruchtsäfte",
        "prezzo": "3.00€",
        "immagine": "assets/piatti/succhi_frutta.webp"
    },
    {
        "categoria": "da bere",
        "nome": "Peroni Bier – 0.62l",
        "prezzo": "6.00€",
        "immagine": "assets/piatti/birra_peroni_066l.webp"
    },
    {
        "categoria": "da bere",
        "nome": "Ichnusa/Corona Bier – 0.33l",
        "prezzo": "4.00€",
        "immagine": "assets/piatti/birra_ichnusa_corona_033l.webp"
    },
    {
        "categoria": "dessert",
        "nome": "Tiramisu",
        "prezzo": "6.00€",
        "immagine": "assets/piatti/tiramisu.webp"
    },
    {
        "categoria": "dessert",
        "nome": "Panna cotta mit Beeren",
        "prezzo": "6.00€",
        "immagine": "assets/piatti/panna_cotta_frutti_bosco.webp"
    },
    {
        "categoria": "dessert",
        "nome": "Panna cotta mit Bronte-Pistazie",
        "prezzo": "6.00€",
        "immagine": "assets/piatti/panna_cotta_pistacchio.webp"
    },
    {
        "categoria": "dessert",
        "nome": "Crème Caramel",
        "prezzo": "6.00€",
        "immagine": "assets/piatti/creme_caramel.webp"
    },
    {
        "categoria": "dessert",
        "nome": "Millefoglie des Küchenchefs",
        "prezzo": "6.00€",
        "immagine": "assets/piatti/millefoglie.webp"
    },
    {
        "categoria": "dessert",
        "nome": "Schokoladensoufflé mit warmem Kern",
        "prezzo": "6.00€",
        "immagine": "assets/piatti/souffle_cioccolato.webp"
    },
    {
        "categoria": "dessert",
        "nome": "Zitronensorbet",
        "prezzo": "6.00€",
        "immagine": "assets/piatti/sorbetto_limone.webp"
    },
    {
        "categoria": "dessert",
        "nome": "Crème brûlée",
        "prezzo": "6.00€",
        "immagine": "assets/piatti/crema_catalana.webp"
    },
    {
        "categoria": "dessert",
        "nome": "Cherubino-Becher",
        "prezzo": "6.00€",
        "immagine": "assets/piatti/coppa_cherubino.webp"
    },
    {
        "categoria": "dessert",
        "nome": "Cheesecake",
        "prezzo": "6.00€",
        "immagine": "assets/piatti/cheesecake.webp"
    },
    {
        "categoria": "dessert",
        "nome": "Bavarois mit Schokolade und Baileys",
        "prezzo": "6.00€",
        "immagine": "assets/piatti/bavarese_cioccolato_baileys.webp"
    },
    {
        "categoria": "dessert",
        "nome": "Bavarois mit weißer Schokolade, Zitrusfrüchten und Limoncello",
        "prezzo": "6.00€",
        "immagine": "assets/piatti/bavarese_cioccolato_bianco.webp"
    },
    {
        "categoria": "caffetteria",
        "nome": "Espresso",
        "prezzo": "2.00€",
        "immagine": "assets/piatti/caffe_espresso.webp"
    },
    {
        "categoria": "caffetteria",
        "nome": "Entkoffeinierter Kaffee",
        "prezzo": "2.00€",
        "immagine": "assets/piatti/caffe_decaffeinato.webp"
    },
    {
        "categoria": "caffetteria",
        "nome": "Cappuccino",
        "prezzo": "2.50",
        "immagine": "assets/piatti/cappuccino.webp"
    },
    {
        "categoria": "caffetteria",
        "nome": "Caffè Latte",
        "prezzo": "3.00€",
        "immagine": "assets/piatti/caffe_latte.webp"
    },
    {
        "categoria": "caffetteria",
        "nome": "Americano Kaffee",
        "prezzo": "2.50",
        "immagine": "assets/piatti/caffe_americano.webp"
    },
    {
        "categoria": "caffetteria",
        "nome": "Entkoffeinierter Cappuccino",
        "prezzo": "2.50",
        "immagine": "assets/piatti/cappuccino_decaffeinato.webp"
    },
    {
        "categoria": "caffetteria",
        "nome": "Tee/Kamille",
        "prezzo": "2.50",
        "immagine": "assets/piatti/te_camomilla.webp"
    }
]